backend/__init__.py
backend/app.py
backend/suffix.py
backend/dice_package/__init__.py
backend/dice_package/dice.py
backend/test_dice/__init__.py
backend/test_dice/test_dice.py
flaskreactapp-1.0.21.dist-info/METADATA
flaskreactapp-1.0.21.dist-info/WHEEL
flaskreactapp-1.0.21.dist-info/top_level.txt
flaskreactapp-1.0.21.dist-info/RECORD
