Metadata-Version: 2.1
Name: flaskreactapp
Version: 1.0.21
Summary: Flask and react application
Home-page: https://github.com/ilyashnil/flash-react-app
Author: IBM
Author-email: ilyashn@il.ibm.com
License: Apache License 2.0
Classifier: Programming Language :: Python :: 3
Classifier: License :: OSI Approved :: Apache Software License
Classifier: Operating System :: OS Independent
Classifier: Topic :: Scientific/Engineering
Requires-Python: >=3.8
Requires-Dist: coverage
Requires-Dist: flask
